MANIFEST.in
README.md
pyproject.toml
setup.py
alfa_sdk/__init__.py
alfa_sdk/algorithm.py
alfa_sdk/cache.py
alfa_sdk/data.py
alfa_sdk/integration.py
alfa_sdk/secrets.py
alfa_sdk.egg-info/PKG-INFO
alfa_sdk.egg-info/SOURCES.txt
alfa_sdk.egg-info/dependency_links.txt
alfa_sdk.egg-info/requires.txt
alfa_sdk.egg-info/top_level.txt
alfa_sdk/common/__init__.py
alfa_sdk/common/auth.py
alfa_sdk/common/base.py
alfa_sdk/common/exceptions.py
alfa_sdk/common/helpers.py
alfa_sdk/common/session.py
alfa_sdk/common/stores.py
alfa_sdk/common/utils.py
alfa_sdk/common/data/endpoints.json
alfa_sdk/common/lib/__init__.py
alfa_sdk/common/lib/http_session.py
alfa_sdk/resources/__init__.py
alfa_sdk/resources/algorithm.py
alfa_sdk/resources/integration.py
alfa_sdk/resources/meta.py
alfa_sdk/resources/release.py