Metadata-Version: 2.1
Name: alfa-sdk
Version: 0.1.51
Summary: The ALFA SDK for Python
Home-page: https://bitbucket.org/widgetbrain/alfa-sdk-py
Author: Widget Brain
License: Apache License 2.0
Platform: UNKNOWN
Classifier: Development Status :: 3 - Alpha
Classifier: Intended Audience :: Developers
Classifier: Natural Language :: English
Classifier: License :: OSI Approved :: Apache Software License
Classifier: Programming Language :: Python
Classifier: Programming Language :: Python :: 3
Classifier: Programming Language :: Python :: 3.6
Classifier: Programming Language :: Python :: 3.7
Provides-Extra: dev
